intxeger/__init__.py
intxeger/intxeger.py
intxeger/optimize.py
intxeger/core/__init__.py
intxeger/core/base.py
intxeger/core/choice.py
intxeger/core/concatenate.py
intxeger/core/constant.py
intxeger/core/group.py
intxeger/core/repeat.py
intxeger-0.1.1.dist-info/LICENSE
intxeger-0.1.1.dist-info/METADATA
intxeger-0.1.1.dist-info/WHEEL
intxeger-0.1.1.dist-info/top_level.txt
intxeger-0.1.1.dist-info/RECORD
